[{"message":"A valuable opportunity for music lovers and music students in Kerala! Prince Rama Varma's full day music workshop at Irinjalakuda, Thrissur District on Sunday, 2 July. To register, please contact The Director, Varaveena School of Music at 99958 34829.","actions":[{"name":"Like","link":"https://www.facebook.com/2210833262/posts/10154715701503263"},{"name":"Share","link":"https://www.facebook.com/2210833262/posts/10154715701503263"}],"id":"2210833262_10154715701503263","from":{"name":"Lakshmy Menon","id":"10155551699294455"},"type":"photo","picture":"https://scontent.xx.fbcdn.net/v/t1.0-0/s130x130/19396641_10155552975709455_1663623247157077211_n.jpg?oh=96d5dfd78f5d32b02d74c8c0cfc711e4\u0026oe=59D44B6E","link":"https://www.facebook.com/photo.php?fbid=10155552975709455\u0026set=gm.10154715701503263\u0026type=3","created_time":"2017-06-24T03:55:36+0000","updated_time":"2017-06-24T03:55:37+0000"},{"message":"Formal practice of madam Emani Lalitha Krishna..","actions":[{"name":"Like","link":"https://www.facebook.com/2210833262/posts/10154715686688263"},{"name":"Share","link":"https://www.facebook.com/2210833262/posts/10154715686688263"}],"id":"2210833262_10154715686688263","from":{"name":"Venkata Hemanth Kumar Tummunuri","id":"1686863488290053"},"type":"video","picture":"https://scontent.xx.fbcdn.net/v/t15.0-10/s130x130/19509732_1063842907082895_2914476846135377920_n.jpg?oh=247880325fe8f4db3542f355b8321b1f\u0026oe=59CB5A76","link":"https://www.facebook.com/pridelegatostudio/videos/1063842293749623/","created_time":"2017-06-24T03:46:56+0000","updated_time":"2017-06-24T03:46:56+0000"},{"actions":[{"name":"Like","link":"https://www.facebook.com/2210833262/posts/10154713653838263"},{"name":"Share","link":"https://www.facebook.com/2210833262/posts/10154713653838263"}],"id":"2210833262_10154713653838263","from":{"name":"Varadaraj Desikachar","id":"653674984841222"},"type":"video","picture":"https://external.xx.fbcdn.net/safe_image.php?d=AQCPL_rqf90ewDz9\u0026w=130\u0026h=130\u0026url=https%3A%2F%2Fi.ytimg.com%2Fvi%2F_F-k-PFgs3o%2Fmaxresdefault_live.jpg\u0026cfs=1\u0026sx=273\u0026sy=0\u0026sw=720\u0026sh=720\u0026_nc_hash=AQCP2OAHlxem5O6z","link":"https://www.youtube.com/attribution_link?a=auxotYVzDqY\u0026u=%2Fwatch%3Fv%3D_F-k-PFgs3o%26feature%3Dshare","created_time":"2017-06-23T12:44:58+0000","updated_time":"2017-06-24T03:17:50+0000"},{"message":"Mohini Attam Dancer . India.","actions":[{"name":"Like","link":"https://www.facebook.com/2210833262/posts/10154715579973263"},{"name":"Share","link":"https://www.facebook.com/2210833262/posts/10154715579973263"}],"id":"2210833262_10154715579973263","from":{"name":"Kalyani Devanathn","id":"443405796035734"},"type":"photo","picture":"https://scontent.xx.fbcdn.net/v/t1.0-0/s130x130/19399323_443374489372198_7248805235855791471_n.jpg?oh=2b83d2930720c6a2d3fa5260037dcd52\u0026oe=59E16266","link":"https://www.facebook.com/photo.php?fbid=443374489372198\u0026set=gm.10154715579973263\u0026type=3","created_time":"2017-06-24T02:38:52+0000","updated_time":"2017-06-24T02:38:53+0000"},{"message":"Murugha potri","actions":[{"name":"Like","link":"https://www.facebook.com/2210833262/posts/10154715490688263"},{"name":"Share","link":"https://www.facebook.com/2210833262/posts/10154715490688263"}],"id":"2210833262_10154715490688263","from":{"name":"Krishnan Nagalakshmi","id":"1906651286222463"},"type":"video","picture":"https://external.xx.fbcdn.net/safe_image.php?d=AQCv51BRpoz7ca8p\u0026w=130\u0026h=130\u0026url=https%3A%2F%2Fi.ytimg.com%2Fvi%2FJfG8R_krdvw%2Fmaxresdefault.jpg\u0026cfs=1\u0026sx=218\u0026sy=0\u0026sw=720\u0026sh=720\u0026_nc_hash=AQB8f3Cw5udamufk","link":"https://www.youtube.com/attribution_link?a=-4kAg9qxnao\u0026u=%2Fwatch%3Fv%3DJfG8R_krdvw%26feature%3Dshare","created_time":"2017-06-24T02:01:29+0000","updated_time":"2017-06-24T02:01:30+0000"},{"message":"Radhajeyalakshmi","actions":[{"name":"Like","link":"https://www.facebook.com/2210833262/posts/10154715465408263"},{"name":"Share","link":"https://www.facebook.com/2210833262/posts/10154715465408263"}],"id":"2210833262_10154715465408263","from":{"name":"Krishnan Nagalakshmi","id":"1906651286222463"},"type":"video","picture":"https://external.xx.fbcdn.net/safe_image.php?d=AQDB_Wi7nkvjVEwa\u0026w=130\u0026h=130\u0026url=https%3A%2F%2Fi.ytimg.com%2Fvi%2FMrRfyXukHzw%2Fmaxresdefault.jpg\u0026cfs=1\u0026sx=177\u0026sy=0\u0026sw=720\u0026sh=720\u0026_nc_hash=AQDjUVgRlrbs1sq2","link":"https://www.youtube.com/attribution_link?a=Q6cZP5QlmaQ\u0026u=%2Fwatch%3Fv%3DMrRfyXukHzw%26feature%3Dshare","created_time":"2017-06-24T01:44:36+0000","updated_time":"2017-06-24T01:44:37+0000"},{"message":"Soolamangalam","actions":[{"name":"Like","link":"https://www.facebook.com/2210833262/posts/10154715460173263"},{"name":"Share","link":"https://www.facebook.com/2210833262/posts/10154715460173263"}],"id":"2210833262_10154715460173263","from":{"name":"Krishnan Nagalakshmi","id":"1906651286222463"},"type":"video","link":"https://www.youtube.com/attribution_link?a=F4Dwem419qY\u0026u=%2Fwatch%3Fv%3DQoUk3yyhO5I%26feature%3Dshare","created_time":"2017-06-24T01:41:44+0000","updated_time":"2017-06-24T01:41:45+0000"},{"message":"திருஞானசம்பந்தர் இயற்றியது.\nஒவ்வொரு பாராவையும்\nமுதலிலிருந்து பாடினாலும்,\nகடைசியிலிருந்து பாடினாலும்\nஸாஹித்யம் மாறாது.\n\nஇதற்கு மஹாவித்வான் பாலமுரளிக்ருஷ்ணா இசையமைத்திருப்பதும் அதே முறைதான்.\nமுதலிலிருந்து பாடினாலும்\nகடைசியிலிருந்து பாடினாலும்\nஸ்வர அமைப்பு மாறாது.\n\nA Prodigy Singing \nA Prodigy's Song !!!","actions":[{"name":"Like","link":"https://www.facebook.com/2210833262/posts/10154715449103263"},{"name":"Share","link":"https://www.facebook.com/2210833262/posts/10154715449103263"}],"id":"2210833262_10154715449103263","from":{"name":"Srinivasaraghavan Sivarama Sasthrigal","id":"1423727961019231"},"type":"video","picture":"https://external.xx.fbcdn.net/safe_image.php?d=AQDfYwv7tqI8xNFJ\u0026w=130\u0026h=130\u0026url=https%3A%2F%2Fi.ytimg.com%2Fvi%2FJ4tpo2a7tPU%2Fmaxresdefault.jpg\u0026cfs=1\u0026sx=525\u0026sy=0\u0026sw=720\u0026sh=720\u0026_nc_hash=AQDXEwBGeD1_WmsL","link":"https://www.youtube.com/attribution_link?a=nt1Mm-HNTqY\u0026u=%2Fwatch%3Fv%3DJ4tpo2a7tPU%26feature%3Dshare","created_time":"2017-06-24T01:35:25+0000","updated_time":"2017-06-24T01:35:25+0000"},{"actions":[{"name":"Like","link":"https://www.facebook.com/2210833262/posts/10154713539158263"},{"name":"Share","link":"https://www.facebook.com/2210833262/posts/10154713539158263"}],"id":"2210833262_10154713539158263","from":{"name":"Vasantharajan Pattabhiraman","id":"1707867525910090"},"type":"video","picture":"https://external.xx.fbcdn.net/safe_image.php?d=AQA8I6Nh7s13Wi0h\u0026w=130\u0026h=130\u0026url=https%3A%2F%2Fi.ytimg.com%2Fvi%2FpmALSD7bS-M%2Fmaxresdefault.jpg\u0026cfs=1\u0026sx=285\u0026sy=0\u0026sw=720\u0026sh=720\u0026_nc_hash=AQDSimif5d6WpY_7","link":"https://m.youtube.com/watch?v=pmALSD7bS-M","created_time":"2017-06-23T11:40:35+0000","updated_time":"2017-06-23T23:35:04+0000"},{"actions":[{"name":"Like","link":"https://www.facebook.com/2210833262/posts/10154712660413263"},{"name":"Share","link":"https://www.facebook.com/2210833262/posts/10154712660413263"}],"id":"2210833262_10154712660413263","from":{"name":"Bhaskaran Shivaraman","id":"1461425420585630"},"type":"link","picture":"https://external.xx.fbcdn.net/safe_image.php?d=AQCbD4GpxmD7V_Sm\u0026w=130\u0026h=130\u0026url=http%3A%2F%2Fwww.thehindu.com%2Ftodays-paper%2Ftp-features%2Ftp-fridayreview%2Farticle19131003.ece%2FALTERNATES%2FLANDSCAPE_615%2F23frKasinewFRG6C1UNN994jpgjpg\u0026cfs=1\u0026_nc_hash=AQCrVV2_b1KU8vBZ","link":"http://www.thehindu.com/todays-paper/tp-features/tp-fridayreview/dikshitars-varanasi-connection/article19131264.ece","created_time":"2017-06-23T01:45:04+0000","updated_time":"2017-06-23T23:21:48+0000"},{"actions":[{"name":"Like","link":"https://www.facebook.com/2210833262/posts/10154714476938263"},{"name":"Share","link":"https://www.facebook.com/2210833262/posts/10154714476938263"}],"id":"2210833262_10154714476938263","from":{"name":"Venu Narasimhadevara","id":"1978796152337143"},"type":"link","picture":"https://external.xx.fbcdn.net/safe_image.php?d=AQAyewddMm0QgAA0\u0026w=130\u0026h=130\u0026url=https%3A%2F%2Fi.ytimg.com%2Fvi%2FfOQSJj_teNU%2Fmaxresdefault.jpg\u0026cfs=1\u0026sx=483\u0026sy=0\u0026sw=720\u0026sh=720\u0026_nc_hash=AQDfRHQ3IU5RNeMB","link":"https://www.youtube.com/attribution_link?a=lwMc4P5CWZk\u0026u=%2Fwatch%3Fv%3DfOQSJj_teNU%26feature%3Dshare","created_time":"2017-06-23T18:35:33+0000","updated_time":"2017-06-23T18:35:33+0000"},{"actions":[{"name":"Like","link":"https://www.facebook.com/2210833262/posts/10154714475838263"},{"name":"Share","link":"https://www.facebook.com/2210833262/posts/10154714475838263"}],"id":"2210833262_10154714475838263","from":{"name":"Venu Narasimhadevara","id":"1978796152337143"},"type":"video","picture":"https://external.xx.fbcdn.net/safe_image.php?w=130\u0026h=130\u0026url=https%3A%2F%2Fi.ytimg.com%2Fvi%2FEahub6c3Hi4%2Fmaxresdefault.jpg\u0026cfs=1\u0026sx=250\u0026sy=0\u0026sw=720\u0026sh=720\u0026_nc_hash=AQDjyLAjjMRUgo8e","link":"https://www.youtube.com/attribution_link?a=XeQyibACkZI\u0026u=%2Fwatch%3Fv%3DEahub6c3Hi4%26feature%3Dshare","created_time":"2017-06-23T18:34:57+0000","updated_time":"2017-06-23T18:34:58+0000"},{"actions":[{"name":"Like","link":"https://www.facebook.com/2210833262/posts/10154714474073263"},{"name":"Share","link":"https://www.facebook.com/2210833262/posts/10154714474073263"}],"id":"2210833262_10154714474073263","from":{"name":"Venu Narasimhadevara","id":"1978796152337143"},"type":"video","link":"https://www.youtube.com/attribution_link?a=pROS9sUWsLI\u0026u=%2Fwatch%3Fv%3DWKG1fN9JdUE%26feature%3Dshare","created_time":"2017-06-23T18:34:05+0000","updated_time":"2017-06-23T18:34:05+0000"},{"message":"Tearing it apart...","actions":[{"name":"Like","link":"https://www.facebook.com/2210833262/posts/10154714288198263"},{"name":"Share","link":"https://www.facebook.com/2210833262/posts/10154714288198263"}],"id":"2210833262_10154714288198263","from":{"name":"Raghavendran Thottappillil","id":"10212331095366020"},"type":"video","picture":"https://external.xx.fbcdn.net/safe_image.php?d=AQD4oA7r90pccxo1\u0026w=130\u0026h=130\u0026url=https%3A%2F%2Fi.ytimg.com%2Fvi%2FmUFwXqB4iqI%2Fmaxresdefault.jpg\u0026cfs=1\u0026sx=0\u0026sy=0\u0026sw=720\u0026sh=720\u0026_nc_hash=AQA-Y8aLIzsKfn4G","link":"https://www.youtube.com/watch?v=mUFwXqB4iqI","created_time":"2017-06-23T17:19:31+0000","updated_time":"2017-06-23T17:19:31+0000"},{"actions":[{"name":"Like","link":"https://www.facebook.com/2210833262/posts/10154713510263263"},{"name":"Share","link":"https://www.facebook.com/2210833262/posts/10154713510263263"}],"id":"2210833262_10154713510263263","from":{"name":"Narayanan Vedantham","id":"10209513514216206"},"type":"video","picture":"https://scontent.xx.fbcdn.net/v/t15.0-10/s130x130/19365867_675563289299628_3555019197689888768_n.jpg?oh=fedd9f1dacbabb2b70726a9678523507\u0026oe=59E0B09B","link":"https://www.facebook.com/madrasana/videos/675542552635035/","created_time":"2017-06-23T11:21:46+0000","updated_time":"2017-06-23T16:54:06+0000"},{"message":"Ramakrishnan Murthy and Bangalore Carnatic duo M.B. Hariharan and B. Ashok will be honoured with Yuva Purandara Award.","actions":[{"name":"Like","link":"https://www.facebook.com/2210833262/posts/10154712684428263"},{"name":"Share","link":"https://www.facebook.com/2210833262/posts/10154712684428263"}],"id":"2210833262_10154712684428263","from":{"name":"Bhaskaran Shivaraman","id":"1461425420585630"},"type":"link","picture":"https://external.xx.fbcdn.net/safe_image.php?d=AQDd3_vC2lqAercx\u0026w=130\u0026h=130\u0026url=http%3A%2F%2Fwww.thehindu.com%2Ftodays-paper%2Ftp-features%2Ftp-fridayreview%2Farticle19131183.ece%2FALTERNATES%2FLANDSCAPE_615%2F23bgfrmkicmdGGS61UUO233jpgjpg\u0026cfs=1\u0026_nc_hash=AQAuPNMApFX92KyP","link":"http://www.thehindu.com/todays-paper/tp-features/tp-fridayreview/music-festival/article19131186.ece","created_time":"2017-06-23T02:01:34+0000","updated_time":"2017-06-23T16:33:48+0000"},{"actions":[{"name":"Like","link":"https://www.facebook.com/2210833262/posts/10154713952188263"},{"name":"Share","link":"https://www.facebook.com/2210833262/posts/10154713952188263"}],"id":"2210833262_10154713952188263","from":{"name":"Balakrishnan Subramaniam","id":"1577409042282873"},"type":"video","picture":"https://external.xx.fbcdn.net/safe_image.php?d=AQC1Jy9fC5yNkYPT\u0026w=130\u0026h=130\u0026url=https%3A%2F%2Fi.ytimg.com%2Fvi%2Fly_XSBNhOFE%2Fhqdefault.jpg\u0026cfs=1\u0026_nc_hash=AQCctB0BIhKA7IFA","link":"https://www.youtube.com/attribution_link?a=zNsJskisp4w\u0026u=%2Fwatch%3Fv%3Dly_XSBNhOFE%26feature%3Dshare","created_time":"2017-06-23T15:13:52+0000","updated_time":"2017-06-23T15:13:52+0000"},{"actions":[{"name":"Like","link":"https://www.facebook.com/2210833262/posts/10154704010298263"},{"name":"Share","link":"https://www.facebook.com/2210833262/posts/10154704010298263"}],"id":"2210833262_10154704010298263","from":{"name":"Narayanan Vedantham","id":"10209513514216206"},"type":"video","picture":"https://scontent.xx.fbcdn.net/v/t15.0-10/s130x130/19298590_474962316186344_3619596517771313152_n.jpg?oh=8ac6569d981b5c61946262d0a678fc41\u0026oe=59E11748","link":"https://www.facebook.com/navatmanmusiccollective/videos/474948056187770/","created_time":"2017-06-20T02:52:23+0000","updated_time":"2017-06-23T14:06:24+0000"},{"actions":[{"name":"Like","link":"https://www.facebook.com/2210833262/posts/10154713556443263"},{"name":"Share","link":"https://www.facebook.com/2210833262/posts/10154713556443263"}],"id":"2210833262_10154713556443263","from":{"name":"Vijay Pathak","id":"10154801195135885"},"type":"link","picture":"https://scontent.xx.fbcdn.net/v/t1.0-1/p200x200/19420437_821512528007822_8601200314686579020_n.jpg?oh=88013e20d37881aad60ab74e4c48dba0\u0026oe=5A1111C2","link":"https://www.facebook.com/World-of-Indian-Literature-Art-Culture-563456890480055/","created_time":"2017-06-23T11:51:46+0000","updated_time":"2017-06-23T11:51:47+0000"},{"actions":[{"name":"Like","link":"https://www.facebook.com/2210833262/posts/10154713270618263"},{"name":"Share","link":"https://www.facebook.com/2210833262/posts/10154713270618263"}],"id":"2210833262_10154713270618263","from":{"name":"Hima Bindu Paluri","id":"767201763459752"},"type":"video","picture":"https://scontent.xx.fbcdn.net/v/t15.0-10/s130x130/19479135_458389281176999_774623555429072896_n.jpg?oh=fd3358b76dce4a2bd671448eb200be08\u0026oe=59CE437E","link":"https://www.facebook.com/438401519842442/videos/458377861178141/","created_time":"2017-06-23T08:16:26+0000","updated_time":"2017-06-23T08:27:27+0000"},{"actions":[{"name":"Like","link":"https://www.facebook.com/2210833262/posts/10154711171738263"},{"name":"Share","link":"https://www.facebook.com/2210833262/posts/10154711171738263"}],"id":"2210833262_10154711171738263","from":{"name":"Hima Bindu Paluri","id":"767201763459752"},"type":"video","picture":"https://scontent.xx.fbcdn.net/v/t15.0-10/s130x130/19488993_458053671210560_2655292294424428544_n.jpg?oh=7a3567cd87081c451aa4b0204e74a2ce\u0026oe=59E71452","link":"https://www.facebook.com/438401519842442/videos/458043514544909/","created_time":"2017-06-22T14:56:47+0000","updated_time":"2017-06-23T08:15:45+0000"},{"message":"Dr BMK\nMegharanjani tevaram","actions":[{"name":"Like","link":"https://www.facebook.com/2210833262/posts/10154713017413263"},{"name":"Share","link":"https://www.facebook.com/2210833262/posts/10154713017413263"}],"id":"2210833262_10154713017413263","from":{"name":"Varadaraj Desikachar","id":"653674984841222"},"type":"video","picture":"https://external.xx.fbcdn.net/safe_image.php?d=AQDfYwv7tqI8xNFJ\u0026w=130\u0026h=130\u0026url=https%3A%2F%2Fi.ytimg.com%2Fvi%2FJ4tpo2a7tPU%2Fmaxresdefault.jpg\u0026cfs=1\u0026sx=525\u0026sy=0\u0026sw=720\u0026sh=720\u0026_nc_hash=AQDXEwBGeD1_WmsL","link":"https://www.youtube.com/attribution_link?a=Dqa27n7lFqk\u0026u=%2Fwatch%3Fv%3DJ4tpo2a7tPU%26feature%3Dshare","created_time":"2017-06-23T05:44:04+0000","updated_time":"2017-06-23T05:44:05+0000"},{"actions":[{"name":"Like","link":"https://www.facebook.com/2210833262/posts/10154712998713263"},{"name":"Share","link":"https://www.facebook.com/2210833262/posts/10154712998713263"}],"id":"2210833262_10154712998713263","from":{"name":"Srinivasaraghavan Sivarama Sasthrigal","id":"1423727961019231"},"type":"video","picture":"https://external.xx.fbcdn.net/safe_image.php?d=AQDFb1u5s4g7czBM\u0026w=130\u0026h=130\u0026url=https%3A%2F%2Fi.ytimg.com%2Fvi%2FV1pxLNTigw8%2Fmaxresdefault.jpg\u0026cfs=1\u0026sx=143\u0026sy=0\u0026sw=720\u0026sh=720\u0026_nc_hash=AQD7ljIT0nKdaYa7","link":"https://www.youtube.com/attribution_link?a=k3PZcopiS4s\u0026u=%2Fwatch%3Fv%3DV1pxLNTigw8%26feature%3Dshare","created_time":"2017-06-23T05:24:22+0000","updated_time":"2017-06-23T05:24:23+0000"},{"actions":[{"name":"Like","link":"https://www.facebook.com/2210833262/posts/10154712918088263"},{"name":"Share","link":"https://www.facebook.com/2210833262/posts/10154712918088263"}],"id":"2210833262_10154712918088263","from":{"name":"Krishna Vaasistha","id":"1535963156461901"},"type":"photo","picture":"https://scontent.xx.fbcdn.net/v/t1.0-0/s130x130/19399793_617383218469845_5215375200956018072_n.jpg?oh=3b9a1a32b88e1ce62f84b283416cb4bb\u0026oe=59D7B5BE","link":"https://www.facebook.com/raorsharath18/photos/a.263297670545070.1073741829.233913130150191/617383218469845/?type=3","created_time":"2017-06-23T04:20:56+0000","updated_time":"2017-06-23T04:20:57+0000"},{"message":"eSwara.org presents!","actions":[{"name":"Like","link":"https://www.facebook.com/2210833262/posts/10154712897773263"},{"name":"Share","link":"https://www.facebook.com/2210833262/posts/10154712897773263"}],"id":"2210833262_10154712897773263","from":{"name":"Mahesh Mudigonda","id":"1536640619689473"},"type":"video","picture":"https://scontent.xx.fbcdn.net/v/t15.0-10/s130x130/19459445_1452716821475943_3983997679356084224_n.jpg?oh=e4dd383983c2a637a7aa164699ab9231\u0026oe=59E4FB2A","link":"https://www.facebook.com/eswara.org/videos/1452696378144654/","created_time":"2017-06-23T04:11:09+0000","updated_time":"2017-06-23T04:11:09+0000"},{"message":"https://youtu.be/vV5nse6kW10","actions":[{"name":"Like","link":"https://www.facebook.com/2210833262/posts/10154712843448263"},{"name":"Share","link":"https://www.facebook.com/2210833262/posts/10154712843448263"}],"id":"2210833262_10154712843448263","from":{"name":"Muppirala Sahithi Priyanka","id":"10154861883558299"},"type":"video","picture":"https://external.xx.fbcdn.net/safe_image.php?d=AQBqC5_kpAYQDBG1\u0026w=130\u0026h=130\u0026url=https%3A%2F%2Fi.ytimg.com%2Fvi%2FvV5nse6kW10%2Fmaxresdefault.jpg\u0026cfs=1\u0026sx=0\u0026sy=0\u0026sw=720\u0026sh=720\u0026_nc_hash=AQCv3J3_MuDPRk-u","link":"https://youtu.be/vV5nse6kW10","created_time":"2017-06-23T03:38:31+0000","updated_time":"2017-06-23T03:38:31+0000"},{"actions":[{"name":"Like","link":"https://www.facebook.com/2210833262/posts/10154711541478263"},{"name":"Share","link":"https://www.facebook.com/2210833262/posts/10154711541478263"}],"id":"2210833262_10154711541478263","from":{"name":"Hima Bindu Paluri","id":"767201763459752"},"type":"video","picture":"https://scontent.xx.fbcdn.net/v/t15.0-10/s130x130/18494080_440056769676917_2257328020710752256_n.jpg?oh=f82d407911017d0f2ce9874ab9961b44\u0026oe=59DF5EA7","link":"https://www.facebook.com/438401519842442/videos/440055046343756/","created_time":"2017-06-22T17:15:23+0000","updated_time":"2017-06-23T03:31:04+0000"},{"message":"https://youtu.be/imTCI4Xl8go","actions":[{"name":"Like","link":"https://www.facebook.com/2210833262/posts/10154712746953263"},{"name":"Share","link":"https://www.facebook.com/2210833262/posts/10154712746953263"}],"id":"2210833262_10154712746953263","from":{"name":"P R Badri Krishnan","id":"10155471047652220"},"type":"video","picture":"https://external.xx.fbcdn.net/safe_image.php?d=AQBTyLmv2y7aFfj2\u0026w=130\u0026h=130\u0026url=https%3A%2F%2Fi.ytimg.com%2Fvi%2FimTCI4Xl8go%2Fmaxresdefault.jpg\u0026cfs=1\u0026sx=0\u0026sy=0\u0026sw=720\u0026sh=720\u0026_nc_hash=AQBv37ajhm04f8yN","link":"https://youtu.be/imTCI4Xl8go","created_time":"2017-06-23T02:41:11+0000","updated_time":"2017-06-23T02:41:11+0000"},{"message":"https://m.youtube.com/watch?v=Zyl7nzWtMJc","actions":[{"name":"Like","link":"https://www.facebook.com/2210833262/posts/10154712700968263"},{"name":"Share","link":"https://www.facebook.com/2210833262/posts/10154712700968263"}],"id":"2210833262_10154712700968263","from":{"name":"S Nagraj Raman","id":"1540470846018911"},"type":"video","picture":"https://external.xx.fbcdn.net/safe_image.php?d=AQCYxQ6Sa9rYzfUc\u0026w=130\u0026h=130\u0026url=https%3A%2F%2Fi.ytimg.com%2Fvi%2FZyl7nzWtMJc%2Fmaxresdefault.jpg\u0026cfs=1\u0026sx=46\u0026sy=0\u0026sw=720\u0026sh=720\u0026_nc_hash=AQDWv6gd2fn4rC4r","link":"https://m.youtube.com/watch?v=Zyl7nzWtMJc","created_time":"2017-06-23T02:12:26+0000","updated_time":"2017-06-23T02:12:27+0000"},{"message":"A special concert by a rare artiste, in a Chamber setting...","actions":[{"name":"Like","link":"https://www.facebook.com/2210833262/posts/10154711955643263"},{"name":"Share","link":"https://www.facebook.com/2210833262/posts/10154711955643263"}],"id":"2210833262_10154711955643263","from":{"name":"Chandrasekaran Vaidyanathan","id":"992040140899523"},"type":"event","picture":"https://scontent.xx.fbcdn.net/v/t1.0-0/q86/c124.0.130.130/p130x130/19366503_1601691006531377_6587718357043273794_n.jpg?oh=2a0f5938ad3a535f2765d9234f2551e0\u0026oe=59C39745","link":"https://www.facebook.com/events/143465822889357/","created_time":"2017-06-22T20:30:01+0000","updated_time":"2017-06-22T20:30:02+0000"},{"message":"https://soundcloud.com/nachiketaji/thoomani-madathu-thiruppavai-hamir-kalyani-sreevalsan-jmenon","actions":[{"name":"Like","link":"https://www.facebook.com/2210833262/posts/10154711774173263"},{"name":"Share","link":"https://www.facebook.com/2210833262/posts/10154711774173263"}],"id":"2210833262_10154711774173263","from":{"name":"Anuroop S Nair","id":"10155260940700499"},"type":"link","picture":"https://external.xx.fbcdn.net/safe_image.php?d=AQCq3KjuNFwMoZbk\u0026w=130\u0026h=130\u0026url=https%3A%2F%2Fi1.sndcdn.com%2Fartworks-000078844471-8ol7od-t500x500.jpg\u0026cfs=1\u0026sx=0\u0026sy=0\u0026sw=500\u0026sh=500\u0026_nc_hash=AQD_Bf36nm6DVHSB","link":"https://soundcloud.com/nachiketaji/thoomani-madathu-thiruppavai-hamir-kalyani-sreevalsan-jmenon","created_time":"2017-06-22T19:03:05+0000","updated_time":"2017-06-22T19:03:06+0000"},{"message":"touching saramati","actions":[{"name":"Like","link":"https://www.facebook.com/2210833262/posts/10154711325673263"},{"name":"Share","link":"https://www.facebook.com/2210833262/posts/10154711325673263"}],"id":"2210833262_10154711325673263","from":{"name":"Narayanan Vedantham","id":"10209513514216206"},"type":"video","picture":"https://external.xx.fbcdn.net/safe_image.php?d=AQCsEWHFOJNBcluI\u0026w=130\u0026h=130\u0026url=https%3A%2F%2Fi.ytimg.com%2Fvi%2FJKs1anhbhws%2Fhqdefault.jpg\u0026cfs=1\u0026sx=87\u0026sy=0\u0026sw=360\u0026sh=360\u0026_nc_hash=AQBYvveLkS9R7KOM","link":"https://www.youtube.com/attribution_link?a=0CKaBKIf9ZQ\u0026u=%2Fwatch%3Fv%3DJKs1anhbhws%26feature%3Dshare","created_time":"2017-06-22T15:44:22+0000","updated_time":"2017-06-22T15:44:23+0000"},{"actions":[{"name":"Like","link":"https://www.facebook.com/2210833262/posts/10154711230918263"},{"name":"Share","link":"https://www.facebook.com/2210833262/posts/10154711230918263"}],"id":"2210833262_10154711230918263","from":{"name":"Venu Narasimhadevara","id":"1978796152337143"},"type":"video","picture":"https://external.xx.fbcdn.net/safe_image.php?d=AQDCFwBoUIwv0P-U\u0026w=130\u0026h=130\u0026url=https%3A%2F%2Fi.ytimg.com%2Fvi%2F95a1EhhnuHM%2Fmaxresdefault.jpg\u0026cfs=1\u0026sx=164\u0026sy=0\u0026sw=720\u0026sh=720\u0026_nc_hash=AQDje-qu3AZpleRS","link":"https://www.youtube.com/attribution_link?a=H6y0M8S6vJ8\u0026u=%2Fwatch%3Fv%3D95a1EhhnuHM%26feature%3Dshare","created_time":"2017-06-22T15:15:29+0000","updated_time":"2017-06-22T15:15:29+0000"},{"actions":[{"name":"Like","link":"https://www.facebook.com/2210833262/posts/10154711210938263"},{"name":"Share","link":"https://www.facebook.com/2210833262/posts/10154711210938263"}],"id":"2210833262_10154711210938263","from":{"name":"Venu Narasimhadevara","id":"1978796152337143"},"type":"video","link":"https://www.youtube.com/attribution_link?a=FBNUzBS4tpE\u0026u=%2Fwatch%3Fv%3DYN0thtc4gQ8%26feature%3Dshare","created_time":"2017-06-22T15:09:09+0000","updated_time":"2017-06-22T15:09:09+0000"},{"actions":[{"name":"Like","link":"https://www.facebook.com/2210833262/posts/10154711185953263"},{"name":"Share","link":"https://www.facebook.com/2210833262/posts/10154711185953263"}],"id":"2210833262_10154711185953263","from":{"name":"Venu Narasimhadevara","id":"1978796152337143"},"type":"video","picture":"https://external.xx.fbcdn.net/safe_image.php?d=AQD5E-M65J8deTQ5\u0026w=130\u0026h=130\u0026url=https%3A%2F%2Fi.ytimg.com%2Fvi%2FA6iMxOPSkLM%2Fmaxresdefault.jpg\u0026cfs=1\u0026sx=270\u0026sy=0\u0026sw=720\u0026sh=720\u0026_nc_hash=AQA1lUuH3i7h_8wW","link":"https://www.youtube.com/attribution_link?a=PU1YnnuIAKU\u0026u=%2Fwatch%3Fv%3DA6iMxOPSkLM%26feature%3Dshare","created_time":"2017-06-22T15:02:49+0000","updated_time":"2017-06-22T15:02:50+0000"},{"actions":[{"name":"Like","link":"https://www.facebook.com/2210833262/posts/10154711180783263"},{"name":"Share","link":"https://www.facebook.com/2210833262/posts/10154711180783263"}],"id":"2210833262_10154711180783263","from":{"name":"Venu Narasimhadevara","id":"1978796152337143"},"type":"video","picture":"https://external.xx.fbcdn.net/safe_image.php?d=AQB04ZwxGrIZYUep\u0026w=130\u0026h=130\u0026url=https%3A%2F%2Fi.ytimg.com%2Fvi%2FCea3TTne0mY%2Fhqdefault.jpg\u0026cfs=1\u0026sx=39\u0026sy=0\u0026sw=360\u0026sh=360\u0026_nc_hash=AQAryeodSAg5Zkir","link":"https://www.youtube.com/attribution_link?a=6NtCJ3B9pLQ\u0026u=%2Fwatch%3Fv%3DCea3TTne0mY%26feature%3Dshare","created_time":"2017-06-22T15:01:34+0000","updated_time":"2017-06-22T15:01:34+0000"}]
